hydrachain/__init__.py
hydrachain/app.py
hydrachain/hdc_service.py
hydrachain/native_contracts.py
hydrachain/nc_utils.py
hydrachain/utils.py
hydrachain/consensus/__init__.py
hydrachain/consensus/base.py
hydrachain/consensus/contract.py
hydrachain/consensus/manager.py
hydrachain/consensus/protocol.py
hydrachain/consensus/simulation.py
hydrachain/consensus/synchronizer.py
hydrachain/consensus/utils.py
hydrachain/examples/__init__.py
hydrachain/examples/native/__init__.py
hydrachain/examples/native/fungible/__init__.py
hydrachain/examples/native/fungible/fungible_contract.py
hydrachain/examples/native/fungible/test_fungible_contract.py
hydrachain/examples/native/fungible/test_iou_contract.py
hydrachain-0.3.2.dist-info/DESCRIPTION.rst
hydrachain-0.3.2.dist-info/METADATA
hydrachain-0.3.2.dist-info/RECORD
hydrachain-0.3.2.dist-info/WHEEL
hydrachain-0.3.2.dist-info/entry_points.txt
hydrachain-0.3.2.dist-info/metadata.json
hydrachain-0.3.2.dist-info/top_level.txt
