Metadata-Version: 2.0
Name: hydrachain
Version: 0.3.2
Summary: Permissioned Distributed Ledger based on Ethereum
Home-page: https://github.com/HydraChain/hydrachain
Author: HeikoHeiko
Author-email: heiko@brainbot.com
License: MIT
Keywords: hydrachain
Platform: UNKNOWN
Classifier: Development Status :: 2 - Pre-Alpha
Classifier: Intended Audience :: Developers
Classifier: License :: OSI Approved :: MIT License
Classifier: Natural Language :: English
Classifier: Programming Language :: Python :: 2
Classifier: Programming Language :: Python :: 2.7
Requires-Dist: bitcoin (>=1.1.39)
Requires-Dist: pyethapp (>=1.2.1)
Requires-Dist: rlp (>=0.4.3)
Requires-Dist: secp256k1 (==0.12.1)
Requires-Dist: simpy (==3.0.8)
